ipmongo.py
ipmongo-0.1.3.dist-info/DESCRIPTION.rst
ipmongo-0.1.3.dist-info/RECORD
ipmongo-0.1.3.dist-info/METADATA
ipmongo-0.1.3.dist-info/metadata.json
ipmongo-0.1.3.dist-info/WHEEL
ipmongo-0.1.3.dist-info/top_level.txt
