Metadata-Version: 2.0
Name: ipmongo
Version: 0.1.3
Summary: Provide conversion of ipaddr object for MongoDB
Home-page: https://github.com/wal1ybot/ipmongo
Author: wal1ybot
Author-email: UNKNOWN
License: MIT
Platform: UNKNOWN
Classifier: Intended Audience :: Developers
Classifier: Natural Language :: English
Classifier: License :: OSI Approved :: MIT License
Classifier: Operating System :: OS Independent
Classifier: Programming Language :: Python
Classifier: Programming Language :: Python :: 2.7
Classifier: Topic :: Software Development :: Libraries :: Python Modules
Classifier: Topic :: Database
Classifier: Topic :: System :: Networking
Requires-Dist: pymongo
Requires-Dist: ipaddr
